mumulib/__init__.py
mumulib/consumers.py
mumulib/consumers_test.py
mumulib/mumutypes.py
mumulib/producers.py
mumulib/server.py
mumulib/shaped.py
mumulib/shaped_test.py
mumulib/tags.py
mumulib-1.0.16.dist-info/METADATA
mumulib-1.0.16.dist-info/WHEEL
mumulib-1.0.16.dist-info/top_level.txt
mumulib-1.0.16.dist-info/RECORD
