Metadata-Version: 2.4
Name: mumulib
Version: 1.0.16
Summary: There is no library, squared
Author-email: Donovan Preston <46048+fzzzy@users.noreply.github.com>
Project-URL: Homepage, https://github.com/fzzzy/mumulib
Project-URL: Issues, https://github.com/fzzzy/mumulib/issues
Classifier: Programming Language :: Python :: 3
Classifier: License :: OSI Approved :: MIT License
Classifier: Operating System :: OS Independent
Requires-Python: >=3.12
